
[
  {
    "id": "fireball",
    "name": "Fireball",
    "cost": 2,
    "rarity": "RARE",
    "type": "SPELL",
    "text": "Deal 3 damage to enemy hero.",
    "effectBindings": [
      {
        "trigger": "on_play",
        "effect": "deal_damage",
        "value": 3,
        "targeting": "ENEMY_BOARD_OR_HERO"
      }
    ]
  },
  {
    "id": "wolf_rider",
    "name": "Wolf Rider",
    "cost": 3,
    "power": 4,
    "health": 2,
    "rarity": "COMMON",
    "type": "UNIT",
    "text": "Fast-moving beast.",
    "effectBindings": [
      {
        "trigger": "on_play",
        "effect": "apply_haste",
        "condition": {
            "name": "owner_below_10_health",
            "ref": "owner_below_10_health",
            "description": "Only trigger if owner is below 10 health."
          }
      }
    ]
  },
  {
    "id": "slime",
    "name": "Slime",
    "cost": 1,
    "power": 1,
    "health": 2,
    "rarity": "COMMON",
    "type": "UNIT",
    "text": "Cute jelly.",
    "effectBindings": [
      {
        "trigger": "on_death",
        "effect": "draw_card"
      }
    ]
  },
  {
    "id": "charlotte",
    "name": "Charlotte, the holy servant",
    "cost": 1,
    "power": 1,
    "health": 1,
    "rarity": "LEGENDARY",
    "type": "UNIT",
    "text": "Charlotte.",
    "effectBindings": [
      {
        "trigger": "on_play",
        "effect": "draw_card",
        "value": 2
      }
    ]
  }
  
  
  

]

